kandinsky/__init__.py
kandinsky/api.py
kandinsky.py-2.4.dist-info/LICENSE
kandinsky.py-2.4.dist-info/METADATA
kandinsky.py-2.4.dist-info/WHEEL
kandinsky.py-2.4.dist-info/top_level.txt
kandinsky.py-2.4.dist-info/RECORD
