Metadata-Version: 2.1
Name: kandinsky.py
Version: 2.4
Summary: Reverse Engineered Kandinsky 2.2 API
Author: zenafey
Author-email: zenafey@eugw.ru
License: MIT
License-File: LICENSE
Requires-Dist: requests
Requires-Dist: aiohttp
Requires-Dist: Pillow
Requires-Dist: colorama
